{
	"bboxes": [
		{
			"idx": "6",
			"bbox": [
				958,
				499,
				39,
				37
			]
		},
		{
			"idx": "5",
			"bbox": [
				928,
				464,
				39,
				37
			]
		},
		{
			"idx": "4",
			"bbox": [
				851,
				466,
				40,
				38
			]
		},
		{
			"idx": "3",
			"bbox": [
				805,
				497,
				41,
				38
			]
		},
		{
			"idx": "2",
			"bbox": [
				769,
				463,
				39,
				38
			]
		},
		{
			"idx": "1",
			"bbox": [
				719,
				487,
				38,
				37
			]
		},
		{
			"idx": "0",
			"bbox": [
				690,
				458,
				37,
				34
			]
		}
	]
}