{
	"bboxes": [
		{
			"idx": "6",
			"bbox": [
				737,
				478,
				26,
				25
			]
		},
		{
			"idx": "5",
			"bbox": [
				707,
				443,
				27,
				26
			]
		},
		{
			"idx": "4",
			"bbox": [
				627,
				446,
				24,
				23
			]
		},
		{
			"idx": "3",
			"bbox": [
				591,
				482,
				24,
				24
			]
		},
		{
			"idx": "2",
			"bbox": [
				563,
				451,
				23,
				23
			]
		},
		{
			"idx": "1",
			"bbox": [
				541,
				484,
				22,
				22
			]
		},
		{
			"idx": "0",
			"bbox": [
				520,
				457,
				21,
				21
			]
		}
	],
	"LRTVEC": [
		[
			[
				-3.005260604364439
			],
			[
				0.04602630035032013
			],
			[
				0.9879286140047919
			]
		],
		[
			[
				-0.02377903284352062
			],
			[
				0.01283476943497751
			],
			[
				0.309919066967758
			]
		]
	]
}